{
  "required": true,
  "minVersion": "0.8",
  "package": "net.blay09.mods.balm.mixin",
  "compatibilityLevel": "JAVA_17",
  "mixins": [
    "BalmConfigDataMixin",
    "ChunkMapMixin",
    "CropBlockMixin",
    "DamageSourceAccessor",
    "EntityMixin",
    "FabricCropBlockMixin",
    "FabricStemBlockMixin",
    "LevelMixin",
    "LivingEntityMixin",
    "LootTableMixin",
    "ReloadableServerResourcesMixin",
    "PlayerMixin",
    "ResultSlotMixin",
    "ServerPlayerMixin",
    "SlotAccessor",
    "StemBlockMixin",
    "MinecraftServerMixin"
  ],
  "client": [
    "AbstractClientPlayerMixin",
    "AbstractContainerScreenAccessor",
    "AbstractContainerScreenMixin",
    "BossHealthOverlayMixin",
    "ChatComponentMixin",
    "CheckboxAccessor",
    "ClientPacketListenerMixin",
    "DebugScreenOverlayMixin",
    "EntityModelSetAccessor",
    "EntityModelSetMixin",
    "GuiMixin",
    "ImageButtonAccessor",
    "ItemInHandRendererMixin",
    "KeyboardHandlerMixin",
    "KeyMappingAccessor",
    "LevelRendererMixin",
    "MinecraftMixin",
    "MouseHandlerAccessor",
    "MouseHandlerMixin",
    "PlayerTabOverlayMixin",
    "ScreenAccessor",
    "ModelManagerMixin"
  ],
  "injectors": {
    "defaultRequire": 1
  }
}
